sgextVersion.py
sgext/__init__.py
sgext/_sgext.cpython-311-darwin.so
sgext/from_to.py
sgext/utils.py
sgext/fixtures/__init__.py
sgext/tables/isthmusicityOne_table26_6.zlib
sgext/tables/isthmusicity_table26_6.zlib
sgext/tables/simplicity_table26_6.zlib
sgext-0.9.16.dist-info/METADATA
sgext-0.9.16.dist-info/WHEEL
sgext-0.9.16.dist-info/top_level.txt
sgext-0.9.16.dist-info/RECORD
