Metadata-Version: 2.1
Name: sgext
Version: 0.9.16
Summary: SGEXT is an open-source toolkit for skeletonization and graph analysis
Home-page: https://github.com/phcerdan/SGEXT
Download-URL: https://github.com/phcerdan/SGEXT
Author: Pablo Hernandez-Cerdan
Author-email: pablo.hernandez.cerdan@outlook.com
License: GPLv3
Keywords: SGEXT thinning skeletonization graph complex-networks imaging
Classifier: License :: OSI Approved :: GNU General Public License v3 (GPLv3)
Classifier: Programming Language :: Python
Classifier: Programming Language :: C++
Classifier: Development Status :: 4 - Beta
Classifier: Intended Audience :: Developers
Classifier: Intended Audience :: Education
Classifier: Intended Audience :: Healthcare Industry
Classifier: Intended Audience :: Science/Research
Classifier: Topic :: Scientific/Engineering
Classifier: Topic :: Scientific/Engineering :: Medical Science Apps.
Classifier: Topic :: Scientific/Engineering :: Information Analysis
Classifier: Topic :: Software Development :: Libraries
Classifier: Operating System :: Android
Classifier: Operating System :: Microsoft :: Windows
Classifier: Operating System :: POSIX
Classifier: Operating System :: Unix
Classifier: Operating System :: MacOS
